muffin_sentry/__init__.py
muffin_sentry/plugin.py
muffin_sentry/py.typed
muffin_sentry-2.0.2.dist-info/METADATA
muffin_sentry-2.0.2.dist-info/WHEEL
muffin_sentry-2.0.2.dist-info/RECORD
