Metadata-Version: 2.3
Name: muffin-sentry
Version: 2.0.2
Summary: Sentry Integration for Muffin framework
License: MIT
Keywords: sentry,asyncio,trio,asgi,muffin
Author: Kirill Klenov
Author-email: horneds@gmail.com
Requires-Python: >=3.10,<4.0
Classifier: Development Status :: 5 - Production/Stable
Classifier: Framework :: AsyncIO
Classifier: Framework :: Trio
Classifier: Intended Audience :: Developers
Classifier: License :: OSI Approved :: MIT License
Classifier: Programming Language :: Python
Classifier: Programming Language :: Python :: 3
Classifier: Programming Language :: Python :: 3.10
Classifier: Programming Language :: Python :: 3.11
Classifier: Programming Language :: Python :: 3.12
Classifier: Programming Language :: Python :: 3.13
Classifier: Topic :: Internet :: WWW/HTTP
Requires-Dist: muffin
Requires-Dist: sentry-sdk
Project-URL: Homepage, https://github.com/klen/muffin-sentry
Project-URL: Repository, https://github.com/klen/muffin-sentry
